{
  "generated_at_utc": "2026-07-10T14:57:51.079098+00:00",
  "data_fetched_at_utc": "2026-07-10T14:56:47.032497+00:00",
  "matches_used": 177,
  "k_factor": 26.0,
  "home_advantage": 60.0,
  "starting_rating": 1500.0,
  "recent_form_window": 5,
  "teams": [
    {
      "team_id": 217781,
      "team": "Orange County SC",
      "rating": 1572.1,
      "games_played": 16,
      "wins": 7,
      "draws": 7,
      "losses": 2,
      "delta_recent": 34.1,
      "delta_recent_games": 5,
      "peak_rating": 1572.3,
      "peak_rating_t": 1783207800,
      "longest_win_streak": 2,
      "longest_unbeaten_streak": 7,
      "rank": 1
    },
    {
      "team_id": 41617,
      "team": "FC Tampa Bay Rowdies",
      "rating": 1568.5,
      "games_played": 15,
      "wins": 9,
      "draws": 4,
      "losses": 2,
      "delta_recent": -24.6,
      "delta_recent_games": 5,
      "peak_rating": 1610.4,
      "peak_rating_t": 1780182000,
      "longest_win_streak": 4,
      "longest_unbeaten_streak": 12,
      "rank": 2
    },
    {
      "team_id": 22004,
      "team": "Charleston Battery",
      "rating": 1548.0,
      "games_played": 15,
      "wins": 8,
      "draws": 2,
      "losses": 5,
      "delta_recent": 37.2,
      "delta_recent_games": 5,
      "peak_rating": 1566.3,
      "peak_rating_t": 1782342000,
      "longest_win_streak": 3,
      "longest_unbeaten_streak": 5,
      "rank": 3
    },
    {
      "team_id": 148992,
      "team": "Indy Eleven",
      "rating": 1545.9,
      "games_played": 12,
      "wins": 6,
      "draws": 3,
      "losses": 3,
      "delta_recent": 38.3,
      "delta_recent_games": 5,
      "peak_rating": 1545.9,
      "peak_rating_t": 1783195200,
      "longest_win_streak": 3,
      "longest_unbeaten_streak": 5,
      "rank": 4
    },
    {
      "team_id": 460707,
      "team": "Lexington SC",
      "rating": 1540.5,
      "games_played": 13,
      "wins": 5,
      "draws": 3,
      "losses": 5,
      "delta_recent": 81.0,
      "delta_recent_games": 5,
      "peak_rating": 1540.5,
      "peak_rating_t": 1783202400,
      "longest_win_streak": 3,
      "longest_unbeaten_streak": 3,
      "rank": 5
    },
    {
      "team_id": 285642,
      "team": "Detroit City FC",
      "rating": 1538.8,
      "games_played": 14,
      "wins": 7,
      "draws": 3,
      "losses": 4,
      "delta_recent": 13.3,
      "delta_recent_games": 5,
      "peak_rating": 1538.8,
      "peak_rating_t": 1783036800,
      "longest_win_streak": 2,
      "longest_unbeaten_streak": 3,
      "rank": 6
    },
    {
      "team_id": 217134,
      "team": "San Antonio FC",
      "rating": 1530.7,
      "games_played": 15,
      "wins": 6,
      "draws": 7,
      "losses": 2,
      "delta_recent": -2.0,
      "delta_recent_games": 5,
      "peak_rating": 1543.3,
      "peak_rating_t": 1779582600,
      "longest_win_streak": 2,
      "longest_unbeaten_streak": 6,
      "rank": 7
    },
    {
      "team_id": 310531,
      "team": "New Mexico United",
      "rating": 1528.1,
      "games_played": 13,
      "wins": 6,
      "draws": 3,
      "losses": 4,
      "delta_recent": 39.3,
      "delta_recent_games": 5,
      "peak_rating": 1528.1,
      "peak_rating_t": 1783215000,
      "longest_win_streak": 2,
      "longest_unbeaten_streak": 5,
      "rank": 8
    },
    {
      "team_id": 197071,
      "team": "FC Tulsa",
      "rating": 1514.2,
      "games_played": 13,
      "wins": 5,
      "draws": 4,
      "losses": 4,
      "delta_recent": -9.9,
      "delta_recent_games": 5,
      "peak_rating": 1540.0,
      "peak_rating_t": 1780194600,
      "longest_win_streak": 3,
      "longest_unbeaten_streak": 5,
      "rank": 9
    },
    {
      "team_id": 153498,
      "team": "Sacramento Republic FC",
      "rating": 1511.6,
      "games_played": 13,
      "wins": 5,
      "draws": 4,
      "losses": 4,
      "delta_recent": -15.4,
      "delta_recent_games": 5,
      "peak_rating": 1527.0,
      "peak_rating_t": 1777773600,
      "longest_win_streak": 1,
      "longest_unbeaten_streak": 4,
      "rank": 10
    },
    {
      "team_id": 502355,
      "team": "Rhode Island FC",
      "rating": 1511.1,
      "games_played": 13,
      "wins": 4,
      "draws": 4,
      "losses": 5,
      "delta_recent": 18.0,
      "delta_recent_games": 5,
      "peak_rating": 1523.2,
      "peak_rating_t": 1781388000,
      "longest_win_streak": 2,
      "longest_unbeaten_streak": 3,
      "rank": 11
    },
    {
      "team_id": 197070,
      "team": "Louisville City FC",
      "rating": 1510.5,
      "games_played": 15,
      "wins": 7,
      "draws": 3,
      "losses": 5,
      "delta_recent": 17.9,
      "delta_recent_games": 5,
      "peak_rating": 1559.3,
      "peak_rating_t": 1774740600,
      "longest_win_streak": 4,
      "longest_unbeaten_streak": 4,
      "rank": 12
    },
    {
      "team_id": 23635,
      "team": "Pittsburgh Riverhounds",
      "rating": 1510.1,
      "games_played": 13,
      "wins": 6,
      "draws": 2,
      "losses": 5,
      "delta_recent": 25.0,
      "delta_recent_games": 5,
      "peak_rating": 1538.8,
      "peak_rating_t": 1781996400,
      "longest_win_streak": 3,
      "longest_unbeaten_streak": 4,
      "rank": 13
    },
    {
      "team_id": 325107,
      "team": "Oakland Roots SC",
      "rating": 1506.9,
      "games_played": 15,
      "wins": 5,
      "draws": 6,
      "losses": 4,
      "delta_recent": -18.4,
      "delta_recent_games": 5,
      "peak_rating": 1536.4,
      "peak_rating_t": 1778378400,
      "longest_win_streak": 2,
      "longest_unbeaten_streak": 5,
      "rank": 14
    },
    {
      "team_id": 197065,
      "team": "Colorado Springs Switchbacks FC",
      "rating": 1506.6,
      "games_played": 14,
      "wins": 5,
      "draws": 4,
      "losses": 5,
      "delta_recent": 19.7,
      "delta_recent_games": 5,
      "peak_rating": 1513.0,
      "peak_rating_t": 1773522000,
      "longest_win_streak": 1,
      "longest_unbeaten_streak": 4,
      "rank": 15
    },
    {
      "team_id": 310968,
      "team": "Hartford Athletic",
      "rating": 1506.5,
      "games_played": 14,
      "wins": 4,
      "draws": 7,
      "losses": 3,
      "delta_recent": 3.6,
      "delta_recent_games": 5,
      "peak_rating": 1541.2,
      "peak_rating_t": 1774134000,
      "longest_win_streak": 1,
      "longest_unbeaten_streak": 5,
      "rank": 16
    },
    {
      "team_id": 310532,
      "team": "El Paso Locomotive FC",
      "rating": 1491.0,
      "games_played": 14,
      "wins": 5,
      "draws": 4,
      "losses": 5,
      "delta_recent": -25.8,
      "delta_recent_games": 5,
      "peak_rating": 1575.5,
      "peak_rating_t": 1775948400,
      "longest_win_streak": 4,
      "longest_unbeaten_streak": 5,
      "rank": 17
    },
    {
      "team_id": 154018,
      "team": "Phoenix Rising FC",
      "rating": 1478.1,
      "games_played": 15,
      "wins": 4,
      "draws": 5,
      "losses": 6,
      "delta_recent": -40.1,
      "delta_recent_games": 5,
      "peak_rating": 1536.9,
      "peak_rating_t": 1777762800,
      "longest_win_streak": 3,
      "longest_unbeaten_streak": 4,
      "rank": 18
    },
    {
      "team_id": 218106,
      "team": "Miami FC",
      "rating": 1468.2,
      "games_played": 15,
      "wins": 4,
      "draws": 6,
      "losses": 5,
      "delta_recent": -23.7,
      "delta_recent_games": 5,
      "peak_rating": 1517.6,
      "peak_rating_t": 1775953800,
      "longest_win_streak": 2,
      "longest_unbeaten_streak": 5,
      "rank": 19
    },
    {
      "team_id": 276898,
      "team": "Las Vegas Lights",
      "rating": 1466.1,
      "games_played": 14,
      "wins": 4,
      "draws": 3,
      "losses": 7,
      "delta_recent": 5.0,
      "delta_recent_games": 5,
      "peak_rating": 1502.2,
      "peak_rating_t": 1772938800,
      "longest_win_streak": 1,
      "longest_unbeaten_streak": 3,
      "rank": 20
    },
    {
      "team_id": 310967,
      "team": "Birmingham Legion FC",
      "rating": 1458.1,
      "games_played": 15,
      "wins": 2,
      "draws": 8,
      "losses": 5,
      "delta_recent": -25.5,
      "delta_recent_games": 5,
      "peak_rating": 1511.2,
      "peak_rating_t": 1777764600,
      "longest_win_streak": 1,
      "longest_unbeaten_streak": 5,
      "rank": 21
    },
    {
      "team_id": 405944,
      "team": "Monterey Bay FC",
      "rating": 1458.0,
      "games_played": 15,
      "wins": 4,
      "draws": 3,
      "losses": 8,
      "delta_recent": 36.9,
      "delta_recent_games": 5,
      "peak_rating": 1500.0,
      "peak_rating_t": null,
      "longest_win_streak": 3,
      "longest_unbeaten_streak": 3,
      "rank": 22
    },
    {
      "team_id": 1158835,
      "team": "Brooklyn FC",
      "rating": 1449.9,
      "games_played": 14,
      "wins": 3,
      "draws": 3,
      "losses": 8,
      "delta_recent": 4.0,
      "delta_recent_games": 5,
      "peak_rating": 1510.8,
      "peak_rating_t": 1772998200,
      "longest_win_streak": 1,
      "longest_unbeaten_streak": 2,
      "rank": 23
    },
    {
      "team_id": 310969,
      "team": "Loudoun United FC",
      "rating": 1423.7,
      "games_played": 14,
      "wins": 1,
      "draws": 8,
      "losses": 5,
      "delta_recent": -60.9,
      "delta_recent_games": 5,
      "peak_rating": 1500.0,
      "peak_rating_t": null,
      "longest_win_streak": 1,
      "longest_unbeaten_streak": 6,
      "rank": 24
    },
    {
      "team_id": 1077312,
      "team": "SC Jacksonville",
      "rating": 1357.0,
      "games_played": 15,
      "wins": 0,
      "draws": 4,
      "losses": 11,
      "delta_recent": -41.5,
      "delta_recent_games": 5,
      "peak_rating": 1500.0,
      "peak_rating_t": null,
      "longest_win_streak": 0,
      "longest_unbeaten_streak": 2,
      "rank": 25
    }
  ],
  "season_year": 2026
}